LICENSE
MANIFEST.in
README.rst
setup.py
streetscape/__init__.py
streetscape/core.py
streetscape/util.py
streetscape.egg-info/PKG-INFO
streetscape.egg-info/SOURCES.txt
streetscape.egg-info/dependency_links.txt
streetscape.egg-info/not-zip-safe
streetscape.egg-info/requires.txt
streetscape.egg-info/top_level.txt