Metadata-Version: 1.1
Name: streetscape
Version: 0.2.1
Summary: help to collect panoramic street view in a city
Home-page: http://github.com/yonghah/streetscape
Author: Yongha Hwang
Author-email: ahgnoy@gmail.com
License: MIT
Download-URL: http://github.com/yonghah/streetscape/tarball/0.2.1
Platform: UNKNOWN
